testopwatch/__init__.py
testopwatch/_result.py
testopwatch/_runner.py
testopwatch-0.1.0.dist-info/LICENSE
testopwatch-0.1.0.dist-info/METADATA
testopwatch-0.1.0.dist-info/WHEEL
testopwatch-0.1.0.dist-info/top_level.txt
testopwatch-0.1.0.dist-info/RECORD
